normword_dna/__init__.py
normword_dna/dna.py
normword_dna-2.0.2.dist-info/METADATA
normword_dna-2.0.2.dist-info/WHEEL
normword_dna-2.0.2.dist-info/licenses/LICENSE.txt
normword_dna-2.0.2.dist-info/RECORD
